optimeering_beta/__init__.py
optimeering_beta/api_client.py
optimeering_beta/api_response.py
optimeering_beta/azure_authentication.py
optimeering_beta/configuration.py
optimeering_beta/exceptions.py
optimeering_beta/extras.py
optimeering_beta/logger.py
optimeering_beta/rest.py
optimeering_beta/silent_type_cast.py
optimeering_beta/api/__init__.py
optimeering_beta/api/access_api.py
optimeering_beta/api/predictions_api.py
optimeering_beta/models/__init__.py
optimeering_beta/models/access_key_created.py
optimeering_beta/models/access_key_post_response.py
optimeering_beta/models/access_post_key.py
optimeering_beta/models/end.py
optimeering_beta/models/expires_at.py
optimeering_beta/models/http_validation_error.py
optimeering_beta/models/max_event_time.py
optimeering_beta/models/predictions_data.py
optimeering_beta/models/predictions_data_list.py
optimeering_beta/models/predictions_event.py
optimeering_beta/models/predictions_series.py
optimeering_beta/models/predictions_series_list.py
optimeering_beta/models/predictions_value.py
optimeering_beta/models/predictions_version.py
optimeering_beta/models/predictions_version_list.py
optimeering_beta/models/start.py
optimeering_beta/models/validation_error.py
optimeering_beta/models/validation_error_loc_inner.py
optimeering_beta/models/versioned_series.py
optimeering_beta-0.1.3.dist-info/METADATA
optimeering_beta-0.1.3.dist-info/WHEEL
optimeering_beta-0.1.3.dist-info/namespace_packages.txt
optimeering_beta-0.1.3.dist-info/top_level.txt
optimeering_beta-0.1.3.dist-info/RECORD
